downloader/__init__.py
downloader/download.py
CrystalDownloader-1.0.2.dist-info/METADATA
CrystalDownloader-1.0.2.dist-info/WHEEL
CrystalDownloader-1.0.2.dist-info/top_level.txt
CrystalDownloader-1.0.2.dist-info/RECORD
