Metadata-Version: 2.1
Name: CrystalDownloader
Version: 1.0.2
Summary: downloader
Home-page: UNKNOWN
Author: crystal
Author-email: zhuhuiping@shizhuang-inc.com
License: Apache License 2.0
Platform: UNKNOWN
Requires-Python: >=3.7
